{"errors":[],"warnings":[],"namedChunkGroups":{"app":{"chunks":[5,2,1],"assets":["webpack-runtime-8bd18fd8507fe0eb90ed.js","webpack-runtime-8bd18fd8507fe0eb90ed.js.map","commons-e6c8d5c814fb37f6a791.js","commons-e6c8d5c814fb37f6a791.js.map","app-38288093eb388363430d.js","app-38288093eb388363430d.js.map"],"children":{},"childAssets":{}},"component---src-pages-404-js":{"chunks":[0,3],"assets":["styles.598bd4229aaf585b7e1f.css","styles-c28398c53fe5547ff027.js","styles-c28398c53fe5547ff027.js.map","component---src-pages-404-js-d3502e1067eb3e37532d.js","component---src-pages-404-js-d3502e1067eb3e37532d.js.map"],"children":{},"childAssets":{}},"component---src-pages-index-js":{"chunks":[0,4],"assets":["styles.598bd4229aaf585b7e1f.css","styles-c28398c53fe5547ff027.js","styles-c28398c53fe5547ff027.js.map","component---src-pages-index-js-2d02588034c3cb4f1d25.js","component---src-pages-index-js-2d02588034c3cb4f1d25.js.map"],"children":{},"childAssets":{}}},"assetsByChunkName":{"app":["webpack-runtime-8bd18fd8507fe0eb90ed.js","commons-e6c8d5c814fb37f6a791.js","app-38288093eb388363430d.js"],"component---src-pages-404-js":["styles.598bd4229aaf585b7e1f.css","styles-c28398c53fe5547ff027.js","component---src-pages-404-js-d3502e1067eb3e37532d.js"],"component---src-pages-index-js":["styles.598bd4229aaf585b7e1f.css","styles-c28398c53fe5547ff027.js","component---src-pages-index-js-2d02588034c3cb4f1d25.js"]}}